Workbook

Sheet Sales Data
A1: NEXACORE RETAIL — Month 2 Week 5 Dataset (Clean — 200 Rows)
A2: Same clean structure as Week 4. This week you learn SUMIFS, COUNTIFS, and XLOOKUP — the tools that answer multi-condition business questions instantly.
A3: Transaction ID | B3: Date | C3: Month | D3: Sales Rep | E3: Region | F3: Product Category | G3: Product | H3: Units Sold | I3: Unit Price ($) | J3: Revenue ($) | K3: Customer Segment
A4: TXN-001 | B4: 2026-02-02 | C4: February | D4: Robert Brown | E4: South | F4: Clothing | G4: Levi Jeans | H4: 1 | I4: 79 | J4: 79 | K4: Standard
A5: TXN-002 | B5: 2026-03-03 | C5: March | D5: Chris Anderson | E5: East | F5: Home Appliances | G5: Instant Pot | H5: 2 | I5: 129 | J5: 258 | K5: Budget
A6: TXN-003 | B6: 2026-04-04 | C6: April | D6: Amanda Thomas | E6: West | F6: Beauty | G6: Tatcha Serum | H6: 1 | I6: 88 | J6: 88 | K6: Premium
A7: TXN-004 | B7: 2026-05-05 | C7: May | D7: Sarah Connor | E7: North | F7: Sports | G7: TRX System | H7: 3 | I7: 179 | J7: 537 | K7: Standard
A8: TXN-005 | B8: 2026-06-06 | C8: June | D8: Lisa Martinez | E8: South | F8: Electronics | G8: Sony Headphones | H8: 1 | I8: 349 | J8: 349 | K8: Budget
A9: TXN-006 | B9: 2026-01-07 | C9: January | D9: David Lee | E9: East | F9: Clothing | G9: Nike Hoodie | H9: 2 | I9: 89 | J9: 178 | K9: Premium
A10: TXN-007 | B10: 2026-02-08 | C10: February | D10: Joshua Jackson | E10: West | F10: Home Appliances | G10: KitchenAid Mixer | H10: 1 | I10: 399 | J10: 399 | K10: Standard
A11: TXN-008 | B11: 2026-03-09 | C11: March | D11: Mike Johnson | E11: North | F11: Beauty | G11: MAC Lipstick | H11: 1 | I11: 24 | J11: 24 | K11: Budget
A12: TXN-009 | B12: 2026-04-10 | C12: April | D12: Emily Davis | E12: South | F12: Sports | G12: Yeti Cooler | H12: 2 | I12: 249 | J12: 498 | K12: Premium
A13: TXN-010 | B13: 2026-05-11 | C13: May | D13: Jennifer Taylor | E13: East | F13: Electronics | G13: Dell Laptop | H13: 1 | I13: 1099 | J13: 1099 | K13: Standard
A14: TXN-011 | B14: 2026-06-12 | C14: June | D14: Ashley White | E14: West | F14: Clothing | G14: Ralph Lauren Polo | H14: 1 | I14: 95 | J14: 95 | K14: Budget
A15: TXN-012 | B15: 2026-01-13 | C15: January | D15: James Wilson | E15: North | F15: Home Appliances | G15: Dyson Vacuum | H15: 2 | I15: 549 | J15: 1098 | K15: Premium
... A203: TXN-200 | B203: 2026-03-05 | C203: March | D203: Mike Johnson | E203: North | F203: Electronics | G203: Samsung TV | H203: 1 | I203: 1299 | J203: 1299 | K203: Budget

Sheet SUMIFS Practice
A1: Week 5 — SUMIFS Practice
A2: SUMIFS sums values that meet MULTIPLE conditions at once. Syntax: =SUMIFS(sum_range, criteria_range1, criteria1, criteria_range2, criteria2, ...)
A4: SECTION 1 — Two Condition SUMIFS
A5: # | B5: Question | C5: Your Formula | D5: Result | E5: Hint
A6: Q1 | C6: SUMIFS('Sales Data'!J4:J203,'Sales Data'!E4:E203,"North",'Sales Data'!C4:C203,"January") | D6: =SUMIFS('Sales Data'!J4:J203,'Sales Data'!E4:E203,"North",'Sales Data'!C4:C203,"January") -> 21504 | E6: =SUMIFS('Sales Data'!J4:J203,'Sales Data'!E4:E203,"North",'Sales Data'!C4:C203,"January") -> 21504
A7: Q2 | B7: Total revenue from Electronics category sold by James Wilson | C7: SUMIFS('Sales Data'!J4:J203,'Sales Data'!F4:F203,"Electronics",'Sales Data'!D4:D203,"James Wilson") | D7: =SUMIFS('Sales Data'!J4:J203,'Sales Data'!F4:F203,"Electronics",'Sales Data'!D4:D203,"James Wilson") -> 2997 | E7: =SUMIFS('Sales Data'!J4:J203,'Sales Data'!F4:F203,"Electronics",'Sales Data'!D4:D203,"James Wilson") -> 2997
A8: Q3 | B8: Total units sold in South region for Premium customers | C8: SUMIFS('Sales Data'!H4:H203,'Sales Data'!E4:E203,"South",'Sales Data'!K4:K203,"Premium") | D8: =SUMIFS('Sales Data'!H4:H203,'Sales Data'!E4:E203,"South",'Sales Data'!K4:K203,"Premium") -> 20 | E8: =SUMIFS('Sales Data'!H4:H203,'Sales Data'!E4:E203,"South",'Sales Data'!K4:K203,"Premium") -> 20
A9: Q4 | B9: Total revenue from Clothing category in East region | C9: SUMIFS('Sales Data'!J4:J203,'Sales Data'!F4:F203,"Clothing",'Sales Data'!E4:E203,"East") | D9: =SUMIFS('Sales Data'!J4:J203,'Sales Data'!F4:F203,"Clothing",'Sales Data'!E4:E203,"East") -> 2452 | E9: =SUMIFS('Sales Data'!J4:J203,'Sales Data'!F4:F203,"Clothing",'Sales Data'!E4:E203,"East") -> 2452
A10: Q5 | B10: Total revenue where units sold is greater than 1 AND category is Sports | C10: SUMIFS('Sales Data'!J4:J203,'Sales Data'!H4:H203,">"&'Sales Data'!H4,'Sales Data'!F4:F203,"Sports") | D10: =SUMIFS('Sales Data'!J4:J203,'Sales Data'!H4:H203,">"&'Sales Data'!H4,'Sales Data'!F4:F203,"Sports") -> 47108 | E10: =SUMIFS('Sales Data'!J4:J203,'Sales Data'!H4:H203,">1",'Sales Data'!F4:F203,"Sports") -> 47108
A12: SECTION 2 — Three Condition SUMIFS (real business complexity)
A13: # | B13: Question | C13: Your Formula | D13: Result | E13: Hint
A14: Q6 | B14: Total revenue from North region, Electronics category, Premium segment | C14: SUMIFS('Sales Data'!J4:J203,'Sales Data'!E4:E203,"North",'Sales Data'!F4:F203,"Electronics",'Sales Data'!K4:K203,"Premium") | D14: =SUMIFS('Sales Data'!J4:J203,'Sales Data'!E4:E203,"North",'Sales Data'!F4:F203,"Electronics",'Sales Data'!K4:K203,"Premium") -> 2997 | E14: =SUMIFS('Sales Data'!J4:J203,'Sales Data'!E4:E203,"North",'Sales Data'!F4:F203,"Electronics",'Sales Data'!K4:K203,"Premium") -> 2997
A15: Q7 | B15: Total revenue from South or East region in February for Sports category | C15: SUMIFS('Sales Data'!J4:J203,'Sales Data'!F4:F203,"Sports",'Sales Data'!E4:E203,"East",'Sales Data'!C4:C203,"February") + SUMIFS('Sales Data'!J4:J203,'Sales Data'!F4:F203,"Sports",'Sales Data'!E4:E203,"South",'Sales Data'!C4:C203,"February") | D15: =SUMIFS('Sales Data'!J4:J203,'Sales Data'!F4:F203,"Sports",'Sales Data'!E4:E203,"East",'Sales Data'!C4:C203,"February") + SUMIFS('Sales Data'!J4:J203,'Sales Data'!F4:F203,"Sports",'Sales Data'!E4:E203,"South",'Sales Data'!C4:C203,"February") -> 2094 | E15: SUMIFS(Sales Data!J4:J203, Sales Data!F4:F203,"Sports", Sales Data!C4:C203,"February") — Note: SUMIFS cannot do OR across one field directly, add two SUMIFS together for South+East
A16: Q8 | B16: Total revenue where unit price is between 100 and 500 | C16: SUMIFS('Sales Data'!J4:J203,'Sales Data'!I4:I203,">100",'Sales Data'!I4:I203,"<500") | D16: =SUMIFS('Sales Data'!J4:J203,'Sales Data'!I4:I203,">100",'Sales Data'!I4:I203,"<500") -> 37850 | E16: =SUMIFS('Sales Data'!J4:J203,'Sales Data'!I4:I203,">=100",'Sales Data'!I4:I203,"<=500") -> 37850

Sheet COUNTIFS Practice
A1: Week 5 — COUNTIFS Practice
A2: COUNTIFS counts rows that meet MULTIPLE conditions at once. Syntax: =COUNTIFS(criteria_range1, criteria1, criteria_range2, criteria2, ...)
A4: SECTION 1 — Two Condition COUNTIFS
A5: # | B5: Question | C5: Your Formula | D5: Result | E5: Hint
A6: Q1 | B6: How many transactions came from North region in Electronics category? | C6: COUNTIFS('Sales Data'!E4:E203,"North",'Sales Data'!F4:F203,"Electronics") | D6: =COUNTIFS('Sales Data'!E4:E203,"North",'Sales Data'!F4:F203,"Electronics") -> 10 | E6: =COUNTIFS('Sales Data'!E4:E203,"North",'Sales Data'!F4:F203,"Electronics") -> 10
A7: Q2 | B7: How many Premium segment orders happened in January? | C7: COUNTIFS('Sales Data'!K4:K203,"Premium",'Sales Data'!C4:C203,"January") | D7: =COUNTIFS('Sales Data'!K4:K203,"Premium",'Sales Data'!C4:C203,"January") -> 33 | E7: =COUNTIFS('Sales Data'!K4:K203,"Premium",'Sales Data'!C4:C203,"January") -> 33
A8: Q3 | B8: How many orders did James Wilson close with more than 1 unit sold? | C8: COUNTIFS('Sales Data'!D4:D203,"James Wilson",'Sales Data'!H4:H203,">"&'Sales Data'!H4) | D8: =COUNTIFS('Sales Data'!D4:D203,"James Wilson",'Sales Data'!H4:H203,">"&'Sales Data'!H4) -> 10 | E8: =COUNTIFS('Sales Data'!D4:D203,"James Wilson",'Sales Data'!H4:H203,">1") -> 10
A9: Q4 | B9: How many Beauty category transactions had revenue below 50? | C9: COUNTIFS('Sales Data'!F4:F203,"Beauty",'Sales Data'!J4:J203,"<"&50) | D9: =COUNTIFS('Sales Data'!F4:F203,"Beauty",'Sales Data'!J4:J203,"<"&50) -> 20 | E9: =COUNTIFS('Sales Data'!F4:F203,"Beauty",'Sales Data'!J4:J203,"<50") -> 20
A10: Q5 | B10: How many transactions in South region were Standard segment? | C10: COUNTIFS('Sales Data'!E4:E203,"South",'Sales Data'!K4:K203,"Standard") | D10: =COUNTIFS('Sales Data'!E4:E203,"South",'Sales Data'!K4:K203,"Standard") -> 17 | E10: =COUNTIFS('Sales Data'!E4:E203,"South",'Sales Data'!K4:K203,"Standard") -> 17
A12: SECTION 2 — COUNTIFS + IF combined (business flagging)
A13: # | B13: Question | C13: Your Formula | D13: Result | E13: Hint
A14: Q6 | B14: Is any single sales rep responsible for more than 20 transactions? Test on James Wilson | C14: IF(COUNTIFS('Sales Data'!D4:D203,"James Wilson")>20,"High","Normal") | D14: =IF(COUNTIFS('Sales Data'!D4:D203,"James Wilson")>20,"High","Normal") -> Normal | E14: =IF(COUNTIFS('Sales Data'!D4:D203,"James Wilson")>20,"High Volume Rep","Normal") -> Normal
A15: Q7 | B15: Flag whether Electronics category has more than 30 transactions total | C15: IF(COUNTIFS('Sales Data'!F4:F203,"Electronics")>30,"High Volume Category","Low Volume Category") | D15: =IF(COUNTIFS('Sales Data'!F4:F203,"Electronics")>30,"High Volume Category","Low Volume Category") -> High Volume Category | E15: =IF(COUNTIFS('Sales Data'!F4:F203,"Electronics")>30,"High Volume Category","Normal Volume") -> High Volume Category
E17: =IF(COUNTIFS('Sales Data'!D4:D203,"James Wilson")>20,"High","Normal") -> Normal

Sheet XLOOKUP Concept
A1: Week 5 — XLOOKUP (Concept + Practice in Real Excel)
A2: XLOOKUP is Excel's newest and most powerful lookup function. This sheet explains it — practice it directly in your Excel app since it requires Excel 365 or Excel 2021+.
A4: WHY XLOOKUP EXISTS
A5: VLOOKUP can only search the first column and only return values to the right.
A6: INDEX MATCH fixes both problems but requires two functions working together.
A7: XLOOKUP does everything INDEX MATCH does but in ONE single function.
A8: XLOOKUP also has a built-in 'not found' message — no need for IFERROR wrapper.
A9: XLOOKUP can search bottom to top or top to bottom — a search direction option VLOOKUP never had.
A11: XLOOKUP SYNTAX
A12: XLOOKUP(lookup_value, lookup_array, return_array, [if_not_found], [match_mode], [search_mode])
A14: Argument | B14: What it does | C14: Example
A15: lookup_value | B15: What you are searching for | D15: "Nike Hoodie"
A16: lookup_array | B16: The single column to search in | D16: 'Sales Data'!G4:G203
A17: return_array | B17: The single column to return from — can be ANY column, not just right side | D17: 'Sales Data'!J4:J203
A18: if_not_found | B18: What to show if no match — replaces the need for IFERROR | D18: "Not Found"
A19: match_mode | B19: Optional — 0 for exact match (default) | D19: 0
A20: search_mode | B20: Optional — 1 for first to last (default) | D20: 1
A22: PRACTICE TASKS — Type these directly in your Excel app on the Sales Data sheet
A23: XT1: In an empty cell type: =XLOOKUP("iPhone 15",G4:G203,J4:J203,"Not Found") — this returns the first revenue value where product is iPhone 15. | F23: returned 999
A24: XT2: Try XLOOKUP searching for a product that does not exist like "iPhone 20". Confirm it returns your 'Not Found' message instead of an error. | F24: used xlookup's if not found logic
A25: XT3: Compare: write the same lookup using VLOOKUP with IFERROR, then using INDEX MATCH, then using XLOOKUP. Time yourself. Which was fastest to write? | F25: xlookup was fastest
A26: XT4: Use XLOOKUP to look LEFT — return the Sales Rep name by searching for a Transaction ID. VLOOKUP cannot do this without rearranging columns. | F26: proved

Sheet Orbitex Callback
A1: Orbitex Callback — What SUMIFS and COUNTIFS Would Have Solved Instantly
A2: Remember Orbitex in Week 2? Several problems that needed manual filtering and multiple IF formulas back then are ONE formula now. This is the payoff of learning new tools.
A4: Then (Week 2) | B4: Now (Week 5) | C4: The Task
A5: Manually filter by city, then filter by category, then count rows one by one | B5: COUNTIFS(Region, "North", Category, "Electronics") | C5: How many North region Electronics orders exist?
A6: Filter by return status, then filter by payment method, then SUM manually | B6: SUMIFS(Revenue, Return, "Yes", Payment, "Credit Card") | C6: Total revenue lost from credit card returns
A7: Write separate IF flags for each condition, then count each flag type manually | B7: COUNTIFS(Category, "Beauty", Revenue, "<50") | C7: How many low value Beauty transactions exist?
A8: Multiple nested IF statements checking region AND category AND date range | B8: SUMIFS(Revenue, Region, "South", Category, "Sports", Month, "February") | C8: Total February Sports revenue in South region
A9: This is what learning compounds into. Every new tool makes the last month's hardest problems trivial. That is the entire point of the roadmap.

Sheet AI Audit
A1: Week 5 — AI Audit Log
A2: Give each SUMIFS/COUNTIFS/XLOOKUP task to AI first. Record what it produced and what it got wrong.
A4: AUDIT 1 — SUMIFS with two conditions
A5: Task given to AI | B5: Total revenue from Electronics category sold by James Wilson
A6: Exact formula AI produced | B6: =SUMIFS(J4:J203,F4:F203,"Electronics",D4:D203,"James Wilson")
A7: Was AI correct? Yes / No | B7: Yes
A8: If No — what was wrong
A9: Error type: Range / Logic / Syntax / Conceptual
A10: How I caught it
A11: What this taught me | B11: ai understands the task's logic better when it is linked with excel file that it can directly access the table and apply logics and formulas
A13: AUDIT 2 — SUMIFS with three conditions
A14: Task given to AI | B14: Total revenue from North region, Electronics category, Premium segment
A15: Exact formula AI produced | B15: =SUMIFS(J4:J203,E4:E203,"North",F4:F203,"Electronics",K4:K203,"Premium")
A16: Was AI correct? Yes / No | B16: Yes
A17: If No — what was wrong
A18: Error type: Range / Logic / Syntax / Conceptual
A19: How I caught it
A20: What this taught me | B20: ai understands the task's logic better when it is linked with excel file that it can directly access the table and apply logics and formulas
A22: AUDIT 3 — COUNTIFS business flagging
A23: Task given to AI | B23: Is any single sales rep responsible for more than 20 transactions? Test on James Wilson
A24: Exact formula AI produced | B24: =IF(COUNTIFS('Sales Data'!D4:D203,"James Wilson")>20,"High","Normal")
A25: Was AI correct? Yes / No | B25: yes
A26: If No — what was wrong
A27: Error type: Range / Logic / Syntax / Conceptual
A28: How I caught it
A29: What this taught me | B29: ai understands the task's logic better when it is linked with excel file that it can directly access the table and apply logics and formulas
A31: AUDIT 4 — XLOOKUP vs VLOOKUP comparison
A32: Task given to AI | B32: use vlookup for Iphone20 return the unit price return Not found if error and on the down cell use xlookup for Iphone20 return the unit price return not found if error
A33: Exact formula AI produced | B33: =IFERROR(VLOOKUP("Iphone20",F4:I203,4,FALSE),"Not Found")&XLOOKUP("Iphone20",G4:G203,I4:I203,"Not Found",0)
A34: Was AI correct? Yes / No | B34: probably yes
A35: If No — what was wrong | B35: the formula syntax was right that it can detect the return we want but one more column was included
A36: Error type: Range / Logic / Syntax / Conceptual | B36: syntax
A37: How I caught it | B37: looking at range it was included one extra column
A38: What this taught me | B38: i guess ai probably checks the true or false first then put the formula woth syntax to prove it so if the return was false it just put the syntax in formula that will return the false anything can be included or missing
